age/__init__.py
age/_version.py
age/cli.py
age/exceptions.py
age/file.py
age/format.py
age/keyloader.py
age/openssh_keys.py
age/stream.py
age/algorithms/__init__.py
age/algorithms/scrypt.py
age/algorithms/ssh_ed25519.py
age/algorithms/ssh_rsa.py
age/algorithms/x25519.py
age/keys/__init__.py
age/keys/agekey.py
age/keys/base.py
age/keys/ed25519.py
age/keys/password.py
age/keys/rsa.py
age/primitives/__init__.py
age/primitives/bech32.py
age/primitives/encode.py
age/primitives/encrypt.py
age/primitives/hashes.py
age/primitives/hkdf.py
age/primitives/hmac.py
age/primitives/random.py
age/primitives/rsa_oaep.py
age/primitives/scrypt.py
age/primitives/x25519.py
age/recipients/__init__.py
age/recipients/base.py
age/recipients/helpers.py
age/recipients/scrypt.py
age/recipients/ssh_ed25519.py
age/recipients/ssh_rsa.py
age/recipients/x25519.py
age/utils/__init__.py
age/utils/asciiarmor.py
age/utils/copy_doc.py
age/utils/env.py
age-0.5.1.dist-info/LICENSE
age-0.5.1.dist-info/METADATA
age-0.5.1.dist-info/WHEEL
age-0.5.1.dist-info/entry_points.txt
age-0.5.1.dist-info/top_level.txt
age-0.5.1.dist-info/RECORD
