Metadata-Version: 2.1
Name: age
Version: 0.5.1
Summary: Actually good encryption. In Python.
Home-page: https://github.com/jojonas/pyage
Author: Jonas Lieb
License: MIT
Project-URL: Repository, https://github.com/jojonas/pyage
Project-URL: Documentation, https://pyage.readthedocs.io/
Project-URL: Specification, https://age-encryption.org/
Keywords: age encryption privacy experimental
Platform: any
Classifier: Development Status :: 3 - Alpha
Classifier: Intended Audience :: Education
Classifier: Intended Audience :: Science/Research
Classifier: License :: OSI Approved :: MIT License
Classifier: Operating System :: OS Independent
Classifier: Environment :: Console
Classifier: Topic :: Security :: Cryptography
Classifier: Programming Language :: Python
Classifier: Programming Language :: Python :: 3 :: Only
Classifier: Programming Language :: Python :: 3.7
Classifier: Programming Language :: Python :: 3.8
Classifier: Programming Language :: Python :: 3.9
Classifier: Programming Language :: Python :: 3.10
Classifier: Programming Language :: Python :: 3.11
Requires-Python: <4,>=3.6
License-File: LICENSE
Requires-Dist: setuptools (>=38.3)
Requires-Dist: pynacl (>=1.4)
Requires-Dist: cryptography (>=2.7)
Requires-Dist: bcrypt (>=3.1)
Requires-Dist: click (>=7.1)
Requires-Dist: requests (>=2.24)
Provides-Extra: dev
Requires-Dist: black ; extra == 'dev'
Requires-Dist: flake8 ; extra == 'dev'
Requires-Dist: mypy ; extra == 'dev'
Requires-Dist: isort ; extra == 'dev'
Requires-Dist: versioneer ; extra == 'dev'
Requires-Dist: types-requests ; extra == 'dev'
Provides-Extra: docs
Requires-Dist: sphinx ; extra == 'docs'
Requires-Dist: doc8 ; extra == 'docs'
Requires-Dist: sphinx-autodoc-typehints ; extra == 'docs'
Requires-Dist: sphinxcontrib-programoutput ; extra == 'docs'
Provides-Extra: test
Requires-Dist: pytest ; extra == 'test'
Requires-Dist: pyfakefs ; extra == 'test'
Requires-Dist: coverage ; extra == 'test'
Requires-Dist: pytest-cov ; extra == 'test'
